pysparkplus/__init__.py
pysparkplus/functions.py
pysparkplus-0.0.3.dist-info/METADATA
pysparkplus-0.0.3.dist-info/WHEEL
pysparkplus-0.0.3.dist-info/LICENSE
pysparkplus-0.0.3.dist-info/RECORD
