Metadata-Version: 2.1
Name: pysparkplus
Version: 0.0.3
Summary: Pyspark extra functions!
Author: wiseupdata
Author-email: silvio.liborio@wiseupdata.com
Requires-Python: >=3.9,<4.0
Classifier: License :: OSI Approved :: MIT License
Classifier: Operating System :: OS Independent
Classifier: Programming Language :: Python :: 3
Classifier: Programming Language :: Python :: 3.9
Classifier: Programming Language :: Python :: 3.10
Classifier: Programming Language :: Python :: 3.11
Classifier: Programming Language :: Python :: 3
Requires-Dist: pyspark (>=3.4.0,<4.0.0)
Requires-Dist: strplus (>=1.0.8,<2.0.0)
